{
"type": "FeatureCollection",
"name": "pontos_apoio",
"crs": { "type": "name", "properties": { "name": "urn:ogc:def:crs:EPSG::4674" } },
"features": [
{ "type": "Feature", "properties": { "ponto": 1 }, "geometry": { "type": "Point", "coordinates": [ -48.579950000000473, -0.755222308396344 ] } },
{ "type": "Feature", "properties": { "ponto": 2 }, "geometry": { "type": "Point", "coordinates": [ -48.570118509339409, -0.783779151101636 ] } },
{ "type": "Feature", "properties": { "ponto": 3 }, "geometry": { "type": "Point", "coordinates": [ -48.535921829285606, -0.776667097571315 ] } }
]
}
